{
  "generated_utc": "2026-06-27 16:53:23 UTC",
  "report_date": "2026-06-23",
  "note": "COT reflects each Tuesday's positioning, released Fri ~3pm CT. Weekly, lagged bias tool \u2014 not an intraday signal.",
  "errors": [
    "NQ"
  ],
  "contracts": [
    {
      "name": "S&P 500 E-Mini",
      "code": "SP",
      "legacy": [
        {
          "date": "2026-06-23",
          "oi": 192059,
          "noncomm_long": 65968,
          "noncomm_short": 34468,
          "noncomm_spread": 6010,
          "comm_long": 38207,
          "comm_short": 51784,
          "nonrept_long": 81874,
          "nonrept_short": 99796,
          "traders_total": 33,
          "traders_noncomm_long": 5,
          "traders_noncomm_short": 10,
          "traders_comm_long": 14,
          "traders_comm_short": 10
        },
        {
          "date": "2026-06-23",
          "oi": 2881793,
          "noncomm_long": 244536,
          "noncomm_short": 276343,
          "noncomm_spread": 634439,
          "comm_long": 1697078,
          "comm_short": 1780612,
          "nonrept_long": 305739,
          "nonrept_short": 190398,
          "traders_total": 475,
          "traders_noncomm_long": 85,
          "traders_noncomm_short": 73,
          "traders_comm_long": 264,
          "traders_comm_short": 212
        },
        {
          "date": "2026-06-16",
          "oi": 3626468,
          "noncomm_long": 260659,
          "noncomm_short": 429943,
          "noncomm_spread": 784035,
          "comm_long": 2238970,
          "comm_short": 2198566,
          "nonrept_long": 342805,
          "nonrept_short": 213925,
          "traders_total": 492,
          "traders_noncomm_long": 81,
          "traders_noncomm_short": 87,
          "traders_comm_long": 286,
          "traders_comm_short": 224
        },
        {
          "date": "2026-06-16",
          "oi": 464733,
          "noncomm_long": 286207,
          "noncomm_short": 147927,
          "noncomm_spread": 45574,
          "comm_long": 51046,
          "comm_short": 92644,
          "nonrept_long": 81906,
          "nonrept_short": 178587,
          "traders_total": 45,
          "traders_noncomm_long": 13,
          "traders_noncomm_short": 11,
          "traders_comm_long": 18,
          "traders_comm_short": 15
        },
        {
          "date": "2026-06-09",
          "oi": 406911,
          "noncomm_long": 255529,
          "noncomm_short": 147414,
          "noncomm_spread": 12307,
          "comm_long": 51983,
          "comm_short": 77251,
          "nonrept_long": 87093,
          "nonrept_short": 169940,
          "traders_total": 45,
          "traders_noncomm_long": 12,
          "traders_noncomm_short": 12,
          "traders_comm_long": 18,
          "traders_comm_short": 15
        },
        {
          "date": "2026-06-09",
          "oi": 3277786,
          "noncomm_long": 277794,
          "noncomm_short": 449584,
          "noncomm_spread": 772184,
          "comm_long": 1901620,
          "comm_short": 1839108,
          "nonrept_long": 326189,
          "nonrept_short": 216910,
          "traders_total": 494,
          "traders_noncomm_long": 89,
          "traders_noncomm_short": 78,
          "traders_comm_long": 277,
          "traders_comm_short": 220
        }
      ]
    },
    {
      "name": "Russell 2000 E-Mini",
      "code": "RTY",
      "legacy": [
        {
          "date": "2026-06-23",
          "oi": 21582,
          "noncomm_long": 5776,
          "noncomm_short": 10632,
          "noncomm_spread": 35,
          "comm_long": 7929,
          "comm_short": 0,
          "nonrept_long": 7842,
          "nonrept_short": 10915,
          "traders_total": 21,
          "traders_noncomm_long": 6,
          "traders_noncomm_short": 6,
          "traders_comm_long": 9,
          "traders_comm_short": 0
        },
        {
          "date": "2026-06-23",
          "oi": 42875,
          "noncomm_long": 16808,
          "noncomm_short": 15430,
          "noncomm_spread": 1888,
          "comm_long": 23951,
          "comm_short": 25556,
          "nonrept_long": 228,
          "nonrept_short": 1,
          "traders_total": 20,
          "traders_noncomm_long": 5,
          "traders_noncomm_short": 3,
          "traders_comm_long": 6,
          "traders_comm_short": 8
        },
        {
          "date": "2026-06-16",
          "oi": 53594,
          "noncomm_long": 5347,
          "noncomm_short": 36922,
          "noncomm_spread": 6658,
          "comm_long": 16677,
          "comm_short": 2189,
          "nonrept_long": 24912,
          "nonrept_short": 7825,
          "traders_total": 31,
          "traders_noncomm_long": 7,
          "traders_noncomm_short": 13,
          "traders_comm_long": 11,
          "traders_comm_short": 3
        },
        {
          "date": "2026-06-16",
          "oi": 42837,
          "noncomm_long": 16793,
          "noncomm_short": 15392,
          "noncomm_spread": 1888,
          "comm_long": 23928,
          "comm_short": 25556,
          "nonrept_long": 228,
          "nonrept_short": 1,
          "traders_total": 20,
          "traders_noncomm_long": 5,
          "traders_noncomm_short": 3,
          "traders_comm_long": 6,
          "traders_comm_short": 8
        },
        {
          "date": "2026-06-09",
          "oi": 54879,
          "noncomm_long": 4592,
          "noncomm_short": 43355,
          "noncomm_spread": 1249,
          "comm_long": 16971,
          "comm_short": 3218,
          "nonrept_long": 32067,
          "nonrept_short": 7057,
          "traders_total": 35,
          "traders_noncomm_long": 6,
          "traders_noncomm_short": 15,
          "traders_comm_long": 11,
          "traders_comm_short": 5
        },
        {
          "date": "2026-06-09",
          "oi": 42748,
          "noncomm_long": 16773,
          "noncomm_short": 15298,
          "noncomm_spread": 1888,
          "comm_long": 23859,
          "comm_short": 25561,
          "nonrept_long": 228,
          "nonrept_short": 1,
          "traders_total": 20,
          "traders_noncomm_long": 5,
          "traders_noncomm_short": 3,
          "traders_comm_long": 6,
          "traders_comm_short": 8
        }
      ]
    },
    {
      "name": "VIX Futures",
      "code": "VX",
      "legacy": [
        {
          "date": "2026-06-23",
          "oi": 353256,
          "noncomm_long": 79562,
          "noncomm_short": 146336,
          "noncomm_spread": 75772,
          "comm_long": 178074,
          "comm_short": 109231,
          "nonrept_long": 19848,
          "nonrept_short": 21917,
          "traders_total": 192,
          "traders_noncomm_long": 61,
          "traders_noncomm_short": 71,
          "traders_comm_long": 45,
          "traders_comm_short": 43
        },
        {
          "date": "2026-06-16",
          "oi": 408315,
          "noncomm_long": 88285,
          "noncomm_short": 155024,
          "noncomm_spread": 94325,
          "comm_long": 202769,
          "comm_short": 136512,
          "nonrept_long": 22936,
          "nonrept_short": 22454,
          "traders_total": 182,
          "traders_noncomm_long": 51,
          "traders_noncomm_short": 68,
          "traders_comm_long": 53,
          "traders_comm_short": 44
        },
        {
          "date": "2026-06-09",
          "oi": 410412,
          "noncomm_long": 97085,
          "noncomm_short": 171505,
          "noncomm_spread": 81738,
          "comm_long": 204993,
          "comm_short": 132534,
          "nonrept_long": 26596,
          "nonrept_short": 24635,
          "traders_total": 190,
          "traders_noncomm_long": 61,
          "traders_noncomm_short": 71,
          "traders_comm_long": 44,
          "traders_comm_short": 44
        },
        {
          "date": "2026-06-02",
          "oi": 410627,
          "noncomm_long": 111052,
          "noncomm_short": 181004,
          "noncomm_spread": 84123,
          "comm_long": 189934,
          "comm_short": 117261,
          "nonrept_long": 25518,
          "nonrept_short": 28239,
          "traders_total": 184,
          "traders_noncomm_long": 59,
          "traders_noncomm_short": 65,
          "traders_comm_long": 43,
          "traders_comm_short": 42
        },
        {
          "date": "2026-05-26",
          "oi": 384569,
          "noncomm_long": 111823,
          "noncomm_short": 166307,
          "noncomm_spread": 75735,
          "comm_long": 174170,
          "comm_short": 116940,
          "nonrept_long": 22841,
          "nonrept_short": 25587,
          "traders_total": 176,
          "traders_noncomm_long": 55,
          "traders_noncomm_short": 66,
          "traders_comm_long": 40,
          "traders_comm_short": 41
        },
        {
          "date": "2026-05-19",
          "oi": 440175,
          "noncomm_long": 126025,
          "noncomm_short": 181794,
          "noncomm_spread": 85610,
          "comm_long": 199578,
          "comm_short": 146327,
          "nonrept_long": 28962,
          "nonrept_short": 26444,
          "traders_total": 182,
          "traders_noncomm_long": 60,
          "traders_noncomm_short": 68,
          "traders_comm_long": 43,
          "traders_comm_short": 43
        }
      ]
    }
  ]
}